STA-663-Final-Project-SSVD.py
SSVD/__init__.py
SSVD/sources.py
STA_663_Final_Project_SSVD-0.1.2.data/data/my_data/breast_cancer.txt
STA_663_Final_Project_SSVD-0.1.2.data/data/my_data/lung_cancer.txt
STA_663_Final_Project_SSVD-0.1.2.data/data/my_data/ssvd_results.txt
STA_663_Final_Project_SSVD-0.1.2.data/scripts/Start_Project.py
STA_663_Final_Project_SSVD-0.1.2.dist-info/LICENSE
STA_663_Final_Project_SSVD-0.1.2.dist-info/METADATA
STA_663_Final_Project_SSVD-0.1.2.dist-info/WHEEL
STA_663_Final_Project_SSVD-0.1.2.dist-info/top_level.txt
STA_663_Final_Project_SSVD-0.1.2.dist-info/RECORD
