Metadata-Version: 2.1
Name: STA-663-Final-Project-SSVD
Version: 0.1.2
Summary: Optimized Sparse Singular Value Decomposition with Numba
Home-page: https://github.com/jaehyunlee1221/STA-663-Final-Project/SSVD
Author: Jae Hyun Lee, Jingxuan Zhang
Author-email: jaehyun.lee@duke.edu, jingxuan.zhang@duke.edu
License: UNKNOWN
Platform: UNKNOWN
Classifier: Programming Language :: Python :: 3
Classifier: License :: OSI Approved :: MIT License
Classifier: Operating System :: OS Independent
Requires-Python: >=3.6
